Metadata-Version: 2.1
Name: simplefilemirror
Version: 1.0.2
Summary: Simple file mirror
Home-page: https://github.com/HenningUe/simple-file-sync
Author: Henning Uekötter
Author-email: ue.henning@gmail.com
License: MIT License
Classifier: Development Status :: 5 - Production/Stable
Classifier: Intended Audience :: End Users/Desktop
Classifier: License :: OSI Approved :: MIT License
Classifier: Topic :: System :: Filesystems 
Classifier: Operating System :: POSIX :: Linux
Classifier: Operating System :: MacOS :: MacOS X
Classifier: Operating System :: Microsoft :: Windows
Classifier: Programming Language :: Python :: 3
License-File: LICENSE
